Metadata-Version: 2.1
Name: famn-opt
Version: 0.3.3
Summary: Python code to optimise FAM-N pulses for MQMAS experiments
Home-page: https://github.com/hcolaux/famn_opt
Author: hcolaux
Author-email: henri.colaux@normalesup.org
License: GNU GPL
Platform: UNKNOWN
Classifier: Programming Language :: Python :: 3.7
Classifier: Development Status :: 3 - Alpha
Classifier: License :: OSI Approved :: GNU General Public License (GPL)
Classifier: Operating System :: OS Independent
